odoo/addons/mail_notification_clean_status_error/README.rst
odoo/addons/mail_notification_clean_status_error/__init__.py
odoo/addons/mail_notification_clean_status_error/__manifest__.py
odoo/addons/mail_notification_clean_status_error/i18n/mail_notification_clean_status_error.pot
odoo/addons/mail_notification_clean_status_error/models/__init__.py
odoo/addons/mail_notification_clean_status_error/models/mail_notification.py
odoo/addons/mail_notification_clean_status_error/readme/CONTRIBUTORS.rst
odoo/addons/mail_notification_clean_status_error/readme/DESCRIPTION.rst
odoo/addons/mail_notification_clean_status_error/static/description/icon.png
odoo/addons/mail_notification_clean_status_error/static/description/index.html
odoo/addons/mail_notification_clean_status_error/tests/__init__.py
odoo/addons/mail_notification_clean_status_error/tests/test_gc_notifications.py
odoo14_addon_mail_notification_clean_status_error-14.0.1.0.1.dist-info/METADATA
odoo14_addon_mail_notification_clean_status_error-14.0.1.0.1.dist-info/WHEEL
odoo14_addon_mail_notification_clean_status_error-14.0.1.0.1.dist-info/top_level.txt
odoo14_addon_mail_notification_clean_status_error-14.0.1.0.1.dist-info/RECORD
